eslearn/.gitattributes
eslearn/.gitignore
eslearn/README.html
eslearn/README.md
eslearn/Users.md
eslearn/__init__.py
eslearn/app.py
eslearn/base.py
eslearn/eslearn_news.txt
eslearn/model_evaluator.py
eslearn/news.html
eslearn/news.md
eslearn/requirements.txt
eslearn/run.py
eslearn/GUI/__init__.py
eslearn/GUI/easylearn_data_loading_gui.py
eslearn/GUI/easylearn_data_loading_gui.ui
eslearn/GUI/easylearn_data_loading_run.py
eslearn/GUI/easylearn_feature_engineering.py
eslearn/GUI/easylearn_feature_engineering_gui.py
eslearn/GUI/easylearn_feature_engineering_gui.ui
eslearn/GUI/easylearn_feature_engineering_run.py
eslearn/GUI/easylearn_machine_learning_gui.py
eslearn/GUI/easylearn_machine_learning_gui.ui
eslearn/GUI/easylearn_machine_learning_run.py
eslearn/GUI/easylearn_main_gui.py
eslearn/GUI/easylearn_main_gui.ui
eslearn/GUI/easylearn_main_run.py
eslearn/GUI/easylearn_model_evaluation_gui.py
eslearn/GUI/easylearn_model_evaluation_gui.ui
eslearn/GUI/easylearn_model_evaluation_run.py
eslearn/GUI/lc_ui2py_for_data_loading.py
eslearn/GUI/lc_ui2py_for_feature_engineering.py
eslearn/GUI/lc_ui2py_for_machine_learning.py
eslearn/GUI/lc_ui2py_for_main.py
eslearn/GUI/lc_ui2py_for_model_evaluation.py
eslearn/GUI/test/configuration_file.json
eslearn/GUI/test/configuration_file_reg.json
eslearn/GUI/test/demo.json
eslearn/GUI/test/demo_data.xlsx
eslearn/GUI/test/demo_target.xlsx
eslearn/GUI/test/radiomics.json
eslearn/GUI/test/szVShc.json
eslearn/GUI/tests/configuration_file.json
eslearn/GUI/tests/configuration_file_reg.json
eslearn/GUI/tests/demo.json
eslearn/GUI/tests/demo_data.xlsx
eslearn/GUI/tests/demo_target.xlsx
eslearn/GUI/tests/numpytest.json
eslearn/GUI/tests/radiomics.json
eslearn/GUI/tests/szVShc.json
eslearn/IO/__init__.py
eslearn/IO/_freesufer.py
eslearn/IO/el_niiProcessor.py
eslearn/IO/freesufer.py
eslearn/IO/write2nii.py
eslearn/R/.RData
eslearn/R/.Rhistory
eslearn/R/.gitignore
eslearn/R/Decision_curve.R
eslearn/R/Decision_curve1.R
eslearn/R/README.md
eslearn-1.1.8.dist-info/LICENSE
eslearn-1.1.8.dist-info/METADATA
eslearn-1.1.8.dist-info/WHEEL
eslearn-1.1.8.dist-info/top_level.txt
eslearn-1.1.8.dist-info/RECORD
