Metadata-Version: 2.1
Name: eslearn
Version: 1.1.8
Summary: This project is designed for machine learning in resting-state fMRI field
Home-page: https://github.com/easylearn-fmri/
Author: Chao Li; Mengshi Dong
Author-email: lichao19870617@gmail.com
Maintainer: Chao Li; Mengshi Dong
Maintainer-email: lichao19870617@gmail.com
License: MIT License
Platform: all
Classifier: Development Status :: 4 - Beta
Classifier: License :: OSI Approved :: MIT License
Classifier: Intended Audience :: Science/Research
Classifier: Intended Audience :: Education
Classifier: Natural Language :: English
Classifier: Natural Language :: Chinese (Simplified)
Classifier: Programming Language :: Python :: 3
Classifier: Operating System :: OS Independent
Requires-Python: >=3.5
License-File: LICENSE
Requires-Dist: imbalanced-learn
Requires-Dist: joblib
Requires-Dist: requests
Requires-Dist: matplotlib
Requires-Dist: nibabel
Requires-Dist: openpyxl
Requires-Dist: xlrd (==1.2.0)
Requires-Dist: pandas
Requires-Dist: PyQt5
Requires-Dist: PyQt5-sip
Requires-Dist: python-dateutil
Requires-Dist: scikit-learn
Requires-Dist: numpy
Requires-Dist: scipy
Requires-Dist: seaborn
Requires-Dist: progressbar
Requires-Dist: netron
